{
  "version": "7",
  "dialect": "postgresql",
  "entries": [
    {
      "idx": 0,
      "version": "7",
      "when": 1768693667784,
      "tag": "0000_flat_tyrannus",
      "breakpoints": true
    },
    {
      "idx": 1,
      "version": "7",
      "when": 1768763108085,
      "tag": "0001_young_silver_sable",
      "breakpoints": true
    },
    {
      "idx": 2,
      "version": "7",
      "when": 1768848328155,
      "tag": "0002_high_master_mold",
      "breakpoints": true
    },
    {
      "idx": 3,
      "version": "7",
      "when": 1768853808722,
      "tag": "0003_sharp_eternity",
      "breakpoints": true
    },
    {
      "idx": 4,
      "version": "7",
      "when": 1769000000000,
      "tag": "0004_time_off_requests",
      "breakpoints": true
    },
    {
      "idx": 5,
      "version": "7",
      "when": 1782081325744,
      "tag": "0005_vengeful_fallen_one",
      "breakpoints": true
    },
    {
      "idx": 6,
      "version": "7",
      "when": 1782082000000,
      "tag": "0006_compliance_saas",
      "breakpoints": true
    },
    {
      "idx": 7,
      "version": "7",
      "when": 1782083000000,
      "tag": "0007_admin_onboarding",
      "breakpoints": true
    },
    {
      "idx": 8,
      "version": "7",
      "when": 1782084000000,
      "tag": "0008_admin_email_unique",
      "breakpoints": true
    },
    {
      "idx": 9,
      "version": "7",
      "when": 1782085000000,
      "tag": "0009_employee_email",
      "breakpoints": true
    },
    {
      "idx": 10,
      "version": "7",
      "when": 1782086000000,
      "tag": "0010_company_subscription",
      "breakpoints": true
    },
    {
      "idx": 11,
      "version": "7",
      "when": 1782087000000,
      "tag": "0011_timeclock_breaks",
      "breakpoints": true
    }
  ]
}